watcher_metering_vsphere/drivers.py
watcher_metering_vsphere/opts.py
watcher_metering_vsphere/__init__.py
watcher_metering_vsphere/doc.py
watcher_metering_vsphere/base.py
watcher_metering_vsphere/version.py
watcher_metering_vsphere/tests/_fixtures.py
watcher_metering_vsphere/tests/test_vsphere_wrapper.py
watcher_metering_vsphere/tests/test_vsphere_drivers.py
watcher_metering_vsphere/tests/__init__.py
watcher_metering_vsphere/tests/base.py
watcher_metering_vsphere/tests/test_vsphere_base.py
watcher_metering_vsphere/commands/gen_drivers.py
watcher_metering_vsphere/commands/export_drivers.py
watcher_metering_vsphere/wrappers/vsphere.py
watcher_metering_vsphere/wrappers/__init__.py
python_watcher_metering_vsphere-0.21.13.dist-info/entry_points.txt
python_watcher_metering_vsphere-0.21.13.dist-info/DESCRIPTION.rst
python_watcher_metering_vsphere-0.21.13.dist-info/top_level.txt
python_watcher_metering_vsphere-0.21.13.dist-info/RECORD
python_watcher_metering_vsphere-0.21.13.dist-info/METADATA
python_watcher_metering_vsphere-0.21.13.dist-info/pbr.json
python_watcher_metering_vsphere-0.21.13.dist-info/metadata.json
python_watcher_metering_vsphere-0.21.13.dist-info/WHEEL
python_watcher_metering_vsphere-0.21.13.data/data/etc/watcher-metering/watcher-metering-vsphere.conf.sample
