Metadata-Version: 2.0
Name: python-watcher-metering-vsphere
Version: 0.21.13
Summary: Drivers for the Watcher Metering agent
Home-page: http://www.openstack.org/
Author: OpenStack
Author-email: openstack-dev@lists.openstack.org
License: UNKNOWN
Platform: UNKNOWN
Classifier: Environment :: OpenStack
Classifier: Intended Audience :: Information Technology
Classifier: Intended Audience :: System Administrators
Classifier: License :: OSI Approved :: Apache Software License
Classifier: Operating System :: POSIX :: Linux
Classifier: Programming Language :: Python
Classifier: Programming Language :: Python :: 2
Classifier: Programming Language :: Python :: 2.7
Classifier: Programming Language :: Python :: 2.6
Classifier: Programming Language :: Python :: 3
Classifier: Programming Language :: Python :: 3.3
Classifier: Programming Language :: Python :: 3.4
Requires-Dist: pbr
Requires-Dist: oslo.config
Requires-Dist: oslo.i18n
Requires-Dist: oslo.log
Requires-Dist: requests
Requires-Dist: enum34
Requires-Dist: lxml
Requires-Dist: pyvmomi
